{"_id": "6576da145de647be92c5af54",
    "index": 0,
    "guid": "82fe28bd-64ab-44d1-89c0-6f3a086b94c0",
    "isActive": true,
    "balance": "$1,307.73",
    "picture": "http://placehold.it/32x32",
    "age": 34,
    "eyeColor": "blue",
    "name": "Stone Douglas",
    "gender": "male",
    "company": "MINGA",
    "email": "stonedouglas@minga.com",
    "phone": "+1 (834) 405-3730",
    "address": "342 Laurel Avenue, Lloyd, Oregon, 9842",
    "about": "Ad cillum id laboris consequat labore minim et sint esse veniam dolore incididunt. Quis enim irure eu fugiat nulla sit duis reprehenderit qui sunt aute. Anim do laborum et eu nisi laboris Lorem excepteur eiusmod. Aute laborum reprehenderit eu aliquip minim ad labore qui.\r\n",
    "registered": "2022-05-21T03:08:38 -02:00"
}